docs/images/IDE_SetSrc.png
runtime_syspath/__init__.py
runtime_syspath/py.typed
runtime_syspath/syspath_path_utils.py
runtime_syspath/syspath_sleuth/__init__.py
runtime_syspath/syspath_sleuth/__main__.py
runtime_syspath/syspath_sleuth/py.typed
runtime_syspath/syspath_sleuth/syspath_sleuth.py
runtime_syspath/syspath_utils.py
runtime_syspath-0.2.14.dist-info/entry_points.txt
runtime_syspath-0.2.14.dist-info/WHEEL
runtime_syspath-0.2.14.dist-info/METADATA
runtime_syspath-0.2.14.dist-info/RECORD
