Metadata-Version: 2.1
Name: runtime-syspath
Version: 0.2.14
Summary: Functions show and find each 'src' directory under working directory and add each to sys.path.
Home-page: https://github.com/gkedge/runtime-syspath
License: MIT
Keywords: testing,sys.path,packaging,dependency,pyproject.toml
Author: Greg Kedge
Author-email: gregwork@kedges.com
Requires-Python: >=3.7,<4.0
Classifier: Intended Audience :: Developers
Classifier: License :: OSI Approved :: MIT License
Classifier: Natural Language :: English
Classifier: Operating System :: OS Independent
Classifier: Programming Language :: Python :: 3
Classifier: Programming Language :: Python :: 3.7
Classifier: Programming Language :: Python :: 3.8
Classifier: Programming Language :: Python :: 3.9
Classifier: Topic :: Software Development :: Libraries
Classifier: Topic :: Software Development :: Testing
Classifier: Topic :: Utilities
Requires-Dist: click (>=7.1.2,<8.0.0)
Requires-Dist: diff-match-patch (>=20200713,<20200714)
Requires-Dist: importlib-metadata (>=2.0.0,<3.0.0)
Project-URL: Bug Tracker, https://github.com/gkedge/runtime-syspath/issues
Project-URL: Repository, https://github.com/gkedge/runtime-syspath
